groupgfa
