Metadata-Version: 1.0
Name: groupgfa
Version: 0.3
Summary: Group G
Home-page: https://github.com/caropinzon/groupgFA.git
Author: Carolina Pinzon
Author-email: caropinzon@student.ie.edu
License: MIT
Platform: UNKNOWN
